Metadata-Version: 1.2
Name: KnowledgeDistillation
Version: 1.0.4
Summary: A general knowledge distillation framework
Home-page: https://github.com/DunZhang/KnowledgeDistillation
Author: ZhangDun
Author-email: dunnzhang0@gmail.com
Maintainer: ZhangDun
Maintainer-email: dunnzhang0@gmail.com
License: MIT
Keywords: Transformer Networks BERT XLNet PyTorch NLP deep learning
Platform: UNKNOWN
Classifier: Development Status :: 2 - Pre-Alpha
Classifier: Operating System :: Microsoft :: Windows
Classifier: Operating System :: POSIX
Classifier: Operating System :: Unix
Classifier: Operating System :: MacOS
Classifier: Intended Audience :: Developers
Classifier: Intended Audience :: Science/Research
Classifier: Programming Language :: Python :: 3
Classifier: License :: OSI Approved :: MIT License
Classifier: Topic :: Scientific/Engineering :: Artificial Intelligence
